pyquibbler/__init__.py
pyquibbler/env.py
pyquibbler/exceptions.py
pyquibbler/assignment/__init__.py
pyquibbler/assignment/assignment.py
pyquibbler/assignment/assignment_template.py
pyquibbler/assignment/assignment_to_from_text.py
pyquibbler/assignment/default_value.py
pyquibbler/assignment/exceptions.py
pyquibbler/assignment/overrider.py
pyquibbler/assignment/rounding.py
pyquibbler/assignment/simplify_assignment.py
pyquibbler/assignment/utils.py
pyquibbler/assignment/override_choice/__init__.py
pyquibbler/assignment/override_choice/choice_context.py
pyquibbler/assignment/override_choice/exceptions.py
pyquibbler/assignment/override_choice/override_choice.py
pyquibbler/assignment/override_choice/override_dialog.py
pyquibbler/assignment/override_choice/types.py
pyquibbler/cache/__init__.py
pyquibbler/cache/cache.py
pyquibbler/cache/cache_utils.py
pyquibbler/cache/holistic_cache.py
pyquibbler/cache/shallow/__init__.py
pyquibbler/cache/shallow/dict_cache.py
pyquibbler/cache/shallow/indexable_cache.py
pyquibbler/cache/shallow/shallow_cache.py
pyquibbler/cache/shallow/nd_cache/__init__.py
pyquibbler/cache/shallow/nd_cache/nd_field_array_cache.py
pyquibbler/cache/shallow/nd_cache/nd_indexable_cache.py
pyquibbler/cache/shallow/nd_cache/nd_unstructured_array_cache.py
pyquibbler/cache/shallow/nd_cache/nd_void_cache.py
pyquibbler/debug_utils/__init__.py
pyquibbler/debug_utils/logger.py
pyquibbler/debug_utils/timer.py
pyquibbler/debug_utils/track_instances.py
pyquibbler/file_syncing/__init__.py
pyquibbler/file_syncing/file_syncer.py
pyquibbler/file_syncing/quib_file_syncer.py
pyquibbler/file_syncing/types.py
pyquibbler/function_definitions/__init__.py
pyquibbler/function_definitions/definitions.py
pyquibbler/function_definitions/func_call.py
pyquibbler/function_definitions/func_definition.py
pyquibbler/function_definitions/location.py
pyquibbler/function_definitions/types.py
pyquibbler/function_definitions/utils.py
pyquibbler/function_overriding/__init__.py
pyquibbler-1.0.0.dist-info/METADATA
pyquibbler-1.0.0.dist-info/WHEEL
pyquibbler-1.0.0.dist-info/top_level.txt
pyquibbler-1.0.0.dist-info/RECORD
