Metadata-Version: 2.4
Name: pyquibbler
Version: 1.0.0
Summary: Interactive, reproducible and efficient data analytics
Home-page: https://github.com/Technion-Kishony-lab/quibbler
Author: Kishony lab, Technion Israel Institute of Technology
Author-email: rkishony@technion.ac.il
Classifier: Framework :: Matplotlib
Classifier: Framework :: Jupyter
Classifier: Intended Audience :: Developers
Classifier: Intended Audience :: Education
Classifier: Intended Audience :: Science/Research
Classifier: Intended Audience :: Healthcare Industry
Classifier: Intended Audience :: Information Technology
Classifier: Topic :: Scientific/Engineering
Classifier: Topic :: Scientific/Engineering :: Visualization
Classifier: License :: OSI Approved :: MIT License
Classifier: Programming Language :: Python
Classifier: Operating System :: OS Independent
Requires-Python: >=3.10
Requires-Dist: matplotlib>=3.9.1
Requires-Dist: numpy>=2.0.1
Requires-Dist: varname>=0.13
Requires-Dist: ipynbname>=2021.3.2
Requires-Dist: flask>=2.1.1
Requires-Dist: flask_cors>=3.0.10
Requires-Dist: ipycytoscape
Requires-Dist: ipywidgets>=8.1
Requires-Dist: traitlets
Requires-Dist: IPython
Provides-Extra: dev
Requires-Dist: pytest; extra == "dev"
Requires-Dist: pytest-pep8; extra == "dev"
Requires-Dist: pytest-cov; extra == "dev"
Requires-Dist: pytest-benchmark; extra == "dev"
Requires-Dist: selenium; extra == "dev"
Requires-Dist: requests; extra == "dev"
Requires-Dist: psutil; extra == "dev"
Requires-Dist: pytest-benchmark; extra == "dev"
Provides-Extra: sphinx
Requires-Dist: sphinx; extra == "sphinx"
Requires-Dist: myst-parser; extra == "sphinx"
Requires-Dist: sphinx_rtd_theme; extra == "sphinx"
Dynamic: author
Dynamic: author-email
Dynamic: classifier
Dynamic: description
Dynamic: description-content-type
Dynamic: home-page
Dynamic: provides-extra
Dynamic: requires-dist
Dynamic: requires-python
Dynamic: summary
